omni_storage/__init__.py
omni_storage/base.py
omni_storage/factory.py
omni_storage/gcs.py
omni_storage/local.py
omni_storage/manifest.py
omni_storage/py.typed
omni_storage/s3.py
omni_storage/types.py
omni_storage-0.3.0.dist-info/METADATA
omni_storage-0.3.0.dist-info/WHEEL
omni_storage-0.3.0.dist-info/entry_points.txt
omni_storage-0.3.0.dist-info/licenses/LICENSE
omni_storage-0.3.0.dist-info/RECORD
