Metadata-Version: 2.4
Name: omni-storage
Version: 0.3.0
Summary: A unified Python interface for file storage.
Project-URL: repository, https://github.com/lfnovo/omni-storage
Project-URL: homepage, https://github.com/lfnovo/omni-storage
Project-URL: documentation, https://github.com/lfnovo/omni-storage#readme
Author-email: LUIS NOVO <lfnovo@gmail.com>
License: MIT
License-File: LICENSE
Keywords: amazon-s3,boto3,gcs,google-cloud-storage,s3,storage
Requires-Python: <3.14,>=3.9
Provides-Extra: dev
Requires-Dist: anyio>=3.7.1; extra == 'dev'
Requires-Dist: boto3>=1.28.0; extra == 'dev'
Requires-Dist: faker>=26.0.0; extra == 'dev'
Requires-Dist: google-cloud-storage>=2.16.0; extra == 'dev'
Requires-Dist: pytest-asyncio>=0.25.3; extra == 'dev'
Requires-Dist: pytest-cov>=6.0.0; extra == 'dev'
Requires-Dist: pytest-mock>=3.14.0; extra == 'dev'
Requires-Dist: pytest>=8.3.4; extra == 'dev'
Requires-Dist: ruff>=0.8.4; extra == 'dev'
Provides-Extra: gcs
Requires-Dist: google-cloud-storage>=2.16.0; extra == 'gcs'
Provides-Extra: s3
Requires-Dist: boto3>=1.28.0; extra == 's3'
Provides-Extra: test
Requires-Dist: anyio>=3.7.1; extra == 'test'
Requires-Dist: boto3>=1.28.0; extra == 'test'
Requires-Dist: faker>=26.0.0; extra == 'test'
Requires-Dist: google-cloud-storage>=2.16.0; extra == 'test'
Requires-Dist: pytest-asyncio>=0.25.3; extra == 'test'
Requires-Dist: pytest-cov>=6.0.0; extra == 'test'
Requires-Dist: pytest-mock>=3.14.0; extra == 'test'
Requires-Dist: pytest>=8.3.4; extra == 'test'
